{
  "themes": [
    {
      "name": "传统报刊",
      "file": "1. 传统报刊.md"
    },
    {
      "name": "网络时代",
      "file": "2. 网络时代.md"
    },
    {
      "name": "密集网格",
      "file": "3. 密集网格.md"
    },
    {
      "name": "色彩斑斓",
      "file": "4. 色彩斑斓.md"
    },
    {
      "name": "梦之蓝",
      "file": "5. 梦之蓝.md"
    },
    {
      "name": "方格笔记",
      "file": "6. 方格笔记.md"
    },
    {
      "name": "水墨丹青",
      "file": "7. 水墨丹青.md"
    },
    {
      "name": "诗意阑珊",
      "file": "8.  诗意阑珊.md"
    },
    {
      "name": "学生时代",
      "file": "9. 学生时代.md"
    },
    {
      "name": "绿色森林",
      "file": "10. 绿色森林.md"
    },
    {
      "name": "薄荷清凉",
      "file": "11. 薄荷清凉.md"
    },
    {
      "name": "爱范儿",
      "file": "12. 爱范儿.md"
    },
    {
      "name": "罗老师代码修复版",
      "file": "13. 罗老师代码修复版.md"
    },
    {
      "name": "阿育幻影",
      "file": "14. 阿育幻影.md"
    },
    {
      "name": "阿育",
      "file": "15. 阿育.md"
    },
    {
      "name": "熊默认",
      "file": "16. 熊默认.md"
    },
    {
      "name": "木炭",
      "file": "17. 木炭.md"
    },
    {
      "name": "钴蓝",
      "file": "18. 钴蓝.md"
    },
    {
      "name": "高对比",
      "file": "19. 高对比.md"
    },
    {
      "name": "D 无聊",
      "file": "20. D 无聊.md"
    },
    {
      "name": "深石墨",
      "file": "21. 深石墨.md"
    },
    {
      "name": "默认",
      "file": "22. 默认.md"
    },
    {
      "name": "迪耶奇",
      "file": "23. 迪耶奇.md"
    },
    {
      "name": "德古拉",
      "file": "24. 德古拉.md"
    },
    {
      "name": "双色热力",
      "file": "25. 双色热力.md"
    },
    {
      "name": "双色浅光",
      "file": "26. 双色浅光.md"
    },
    {
      "name": "甘道夫",
      "file": "27. 甘道夫.md"
    },
    {
      "name": "哥谭",
      "file": "28. 哥谭.md"
    },
    {
      "name": "靛蓝",
      "file": "29. 靛蓝.md"
    },
    {
      "name": "杰兹曼",
      "file": "30. 杰兹曼.md"
    },
    {
      "name": "云雀浓彩",
      "file": "31. 云雀浓彩.md"
    },
    {
      "name": "云雀",
      "file": "32. 云雀.md"
    },
    {
      "name": "灯塔",
      "file": "33. 灯塔.md"
    },
    {
      "name": "北境",
      "file": "34. 北境.md"
    },
    {
      "name": "橄榄深色",
      "file": "35. 橄榄深色.md"
    },
    {
      "name": "恐慌",
      "file": "36. 恐慌.md"
    },
    {
      "name": "红石墨",
      "file": "37. 红石墨.md"
    },
    {
      "name": "智能蓝",
      "file": "38. 智能蓝.md"
    },
    {
      "name": "日光暗",
      "file": "39. 日光暗.md"
    },
    {
      "name": "日光亮",
      "file": "40. 日光亮.md"
    },
    {
      "name": "牙膏",
      "file": "41. 牙膏.md"
    },
    {
      "name": "排版",
      "file": "42. 排版.md"
    },
    {
      "name": "V 绿",
      "file": "43. V 绿.md"
    },
    {
      "name": "视图",
      "file": "44. 视图.md"
    },
    {
      "name": "枫叶",
      "file": "45. 枫叶.md"
    },
    {
      "name": "CSSume",
      "file": "CSSume.md"
    },
    {
      "name": "Doocs Default",
      "file": "Doocs - Default.md"
    },
    {
      "name": "Doocs Grace",
      "file": "Doocs - Grace.md"
    },
    {
      "name": "Doocs Simple",
      "file": "Doocs - Simple.md"
    },
    {
      "name": "Markdown CSS (zhangjikai)",
      "file": "Markdown CSS - Zhangjikai.md"
    },
    {
      "name": "Typora Orange Heart Monokai",
      "file": "Typora - Orange Heart Monokai.md"
    },
    {
      "name": "WeCatch Apollo",
      "file": "WeCatch - Apollo.md"
    },
    {
      "name": "WeCatch Ocean",
      "file": "WeCatch - Ocean.md"
    },
    {
      "name": "WeCatch Simple",
      "file": "WeCatch - Simple.md"
    },
    {
      "name": "WeCatch Style",
      "file": "WeCatch - Style.md"
    },
    {
      "name": "WeCatch Typing",
      "file": "WeCatch - Typing.md"
    },
    {
      "name": "WeCatch Xiaolai",
      "file": "WeCatch - Xiaolai.md"
    }
  ]
}
